hanzo_mcp_client/__init__.py
hanzo_mcp_client/client.py
hanzo_mcp_client/config.py
hanzo_mcp_client/tool.py
hanzo_mcp_client/utils.py
hanzo_mcp_client-0.1.0.dist-info/METADATA
hanzo_mcp_client-0.1.0.dist-info/WHEEL
hanzo_mcp_client-0.1.0.dist-info/RECORD
